hv_uploader/__init__.py
hv_uploader-2017.9.27.dist-info/DESCRIPTION.rst
hv_uploader-2017.9.27.dist-info/METADATA
hv_uploader-2017.9.27.dist-info/RECORD
hv_uploader-2017.9.27.dist-info/WHEEL
hv_uploader-2017.9.27.dist-info/entry_points.txt
hv_uploader-2017.9.27.dist-info/metadata.json
hv_uploader-2017.9.27.dist-info/top_level.txt
hv_uploader-2017.9.27.dist-info/zip-safe
