Metadata-Version: 2.0
Name: hv-uploader
Version: 2017.9.27
Summary: Uploads content to the Heavy Cloud Service (https://enzienaudio.com).
Home-page: http://github.com/enzienaudio/hv-uploader
Author: Enzien Audio Ltd
Author-email: info@enzienaudio.com
License: MIT
Keywords: procedural audio uploader heavy enzien audio interactive games
Platform: UNKNOWN
Classifier: License :: OSI Approved :: MIT License
Classifier: Programming Language :: Python :: 2.7
Classifier: Topic :: Utilities
Requires-Dist: requests
